LICENSE
README.md
setup.py
ArtificialVocalLearning/NN.py
ArtificialVocalLearning/__init__.py
ArtificialVocalLearning/learned_states.py
ArtificialVocalLearning/phoneme_classes.py
ArtificialVocalLearning/phoneme_recognition.py
ArtificialVocalLearning/visual_measurements.py
ArtificialVocalLearning/vocal_learning.py
ArtificialVocalLearning/models/RUN_2_tr_KIEL_BITS_te_VTL/weights_best/checkpoint
ArtificialVocalLearning/models/RUN_2_tr_KIEL_BITS_te_VTL/weights_best/checkpoint.data-00000-of-00001
ArtificialVocalLearning/models/RUN_2_tr_KIEL_BITS_te_VTL/weights_best/checkpoint.index
artificial_vocal_learning.egg-info/PKG-INFO
artificial_vocal_learning.egg-info/SOURCES.txt
artificial_vocal_learning.egg-info/dependency_links.txt
artificial_vocal_learning.egg-info/requires.txt
artificial_vocal_learning.egg-info/top_level.txt
artificial_vocal_learning.egg-info/zip-safe