Metadata-Version: 2.1
Name: artificial-vocal-learning
Version: 0.1.13
Summary: A high quality vocal learning simulation for Python
Home-page: https://github.com/paul-krug/artificial-vocal-learning
Author: Paul Krug
Author-email: paul_konstantin.krug@tu-dresden.de
License: UNKNOWN
Keywords: vocal learning,simulation,Python
Platform: UNKNOWN
Classifier: Development Status :: 3 - Alpha
Classifier: Intended Audience :: Science/Research
Classifier: Intended Audience :: Developers
Classifier: License :: OSI Approved :: GNU General Public License v3 (GPLv3)
Classifier: Programming Language :: Python
Classifier: Programming Language :: Python :: 3
Classifier: Programming Language :: Python :: 3.8
Classifier: Programming Language :: Python :: 3.9
Classifier: Topic :: Software Development
Classifier: Topic :: Scientific/Engineering
Classifier: Typing :: Typed
Classifier: Operating System :: Microsoft :: Windows
Classifier: Operating System :: Unix
License-File: LICENSE
